{
	"credit": "Made with Blockbench",
	"textures": {
		"0": "dustydecor:block/cage_lamp_tall",
		"1": "dustydecor:block/cage_lamp_tall_lamp",
		"particle": "dustydecor:block/cage_lamp_tall"
	},
	"elements": [
		{
			"name": "base",
			"from": [5, 0, 5],
			"to": [11, 2, 11],
			"rotation": {"angle": 0, "axis": "y", "origin": [5, 0, 5]},
			"faces": {
				"north": {"uv": [0, 6, 6, 8], "texture": "#0"},
				"east": {"uv": [6, 8, 12, 10], "texture": "#0"},
				"south": {"uv": [0, 8, 6, 10], "texture": "#0"},
				"west": {"uv": [6, 6, 12, 8], "texture": "#0"},
				"up": {"uv": [0, 10, 6, 16], "texture": "#0"},
				"down": {"uv": [0, 10, 6, 16], "texture": "#0"}
			}
		},
		{
			"name": "lamp",
			"from": [6, 2, 6],
			"to": [10, 8, 10],
			"rotation": {"angle": 0, "axis": "y", "origin": [5, 2, 5]},
			"faces": {
				"north": {"uv": [12, 4, 16, 10], "texture": "#1", "tintindex": 0},
				"east": {"uv": [8, 4, 12, 10], "texture": "#1", "tintindex": 0},
				"south": {"uv": [0, 4, 4, 10], "texture": "#1", "tintindex": 0},
				"west": {"uv": [4, 4, 8, 10], "texture": "#1", "tintindex": 0},
				"up": {"uv": [8, 4, 4, 0], "texture": "#1", "tintindex": 0}
			}
		},
		{
			"name": "cage",
			"from": [5, 2, 5],
			"to": [11, 9, 5],
			"rotation": {"angle": 0, "axis": "y", "origin": [5, 2, 5]},
			"faces": {
				"north": {"uv": [6, 10, 13, 16], "rotation": 90, "texture": "#0"},
				"south": {"uv": [6, 10, 13, 16], "rotation": 90, "texture": "#0"}
			}
		},
		{
			"name": "cage",
			"from": [5, 2, 11],
			"to": [11, 9, 11],
			"rotation": {"angle": 0, "axis": "y", "origin": [5, 2, 5]},
			"faces": {
				"north": {"uv": [6, 10, 13, 16], "rotation": 90, "texture": "#0"},
				"south": {"uv": [6, 10, 13, 16], "rotation": 90, "texture": "#0"}
			}
		},
		{
			"name": "cage",
			"from": [11, 2, 5],
			"to": [11, 9, 11],
			"rotation": {"angle": 0, "axis": "y", "origin": [5, 2, 5]},
			"faces": {
				"east": {"uv": [6, 0, 13, 6], "rotation": 90, "texture": "#0"},
				"west": {"uv": [6, 0, 13, 6], "rotation": 90, "texture": "#0"}
			}
		},
		{
			"name": "cage",
			"from": [5, 2, 5],
			"to": [5, 9, 11],
			"rotation": {"angle": 0, "axis": "y", "origin": [5, 2, 5]},
			"faces": {
				"east": {"uv": [6, 0, 13, 6], "rotation": 90, "texture": "#0"},
				"west": {"uv": [6, 0, 13, 6], "rotation": 90, "texture": "#0"}
			}
		},
		{
			"name": "cage",
			"from": [5, 9, 5],
			"to": [11, 9, 11],
			"rotation": {"angle": 0, "axis": "y", "origin": [5, 2, 5]},
			"faces": {
				"up": {"uv": [0, 0, 6, 6], "texture": "#0"},
				"down": {"uv": [0, 0, 6, 6], "texture": "#0"}
			}
		}
	],
	"display": {
		"thirdperson_righthand": {
			"rotation": [75, 45, 0],
			"translation": [0, 1.25, 3],
			"scale": [0.375, 0.375, 0.375]
		},
		"thirdperson_lefthand": {
			"rotation": [75, 45, 0],
			"translation": [0, 1.25, 3],
			"scale": [0.375, 0.375, 0.375]
		},
		"firstperson_righthand": {
			"rotation": [0, 45, 0],
			"translation": [0, 2.5, 0],
			"scale": [0.4, 0.4, 0.4]
		},
		"firstperson_lefthand": {
			"rotation": [0, 225, 0],
			"translation": [0, 2.5, 0],
			"scale": [0.4, 0.4, 0.4]
		},
		"ground": {
			"translation": [0, 3, 0],
			"scale": [0.5, 0.5, 0.5]
		},
		"gui": {
			"rotation": [30, 225, 0],
			"translation": [0, 3.25, 0]
		},
		"head": {
			"translation": [0, 14.25, 0]
		},
		"fixed": {
			"translation": [0, 4, 0]
		}
	},
	"groups": [
		0,
		1,
		{
			"name": "cage",
			"origin": [5, 2, 5],
			"color": 0,
			"children": [2, 3, 4, 5, 6]
		}
	]
}